[{"woord":"De rien.","betekenis":["Graag gedaan."]},{"woord":"Merci et au revoir.","betekenis":["Bedankt en tot ziens."]},{"woord":"Voilà.","betekenis":["Alstublieft."]},{"woord":"Monsieur, l'addition, s'il vous plait.","betekenis":["Ober, de rekening.","Ober, de rekening graag.","Ober, de rekening, alstublieft."]},{"woord":"C'est ici.","betekenis":["Dat is hier."]},{"woord":"Où sont les toilettes?","betekenis":["Waar zijn de wc's?","Waar zijn de toiletten?"]},{"woord":"Un coca et une pizza, s'il vous plait.","betekenis":["Een cola en een pizza alstublieft.","Een cola en een pizza, alstublieft."]},{"woord":"Monsieur, la carte s'il vous plait.","betekenis":["Ober, de kaart alstublieft.","Ober, de kaart, alstublieft."]}]